bitcart/__init__.py
bitcart/coin.py
bitcart/errors.py
bitcart/coins/__init__.py
bitcart/coins/bch.py
bitcart/coins/bsty.py
bitcart/coins/btc.py
bitcart/coins/gzro.py
bitcart/coins/ltc.py
bitcart/providers/__init__.py
bitcart/providers/jsonrpcrequests.py
tests/__init__.py
tests/conftest.py
tests/test_coin.py
tests/coins/__init__.py
tests/coins/test_btc.py
bitcart_async-0.9.1.dist-info/LICENSE
bitcart_async-0.9.1.dist-info/METADATA
bitcart_async-0.9.1.dist-info/WHEEL
bitcart_async-0.9.1.dist-info/top_level.txt
bitcart_async-0.9.1.dist-info/RECORD
