Metadata-Version: 2.1
Name: bitcart-async
Version: 0.9.1
Summary: BitcartCC coins support library
Home-page: https://github.com/MrNaif2018/bitcart-sdk
Author: MrNaif2018
Author-email: chuff184@gmail.com
License: MIT
Keywords: electrum,daemon,bitcart,bitcartcc
Platform: UNKNOWN
Classifier: Development Status :: 3 - Alpha
Classifier: Intended Audience :: Developers
Classifier: Topic :: Software Development :: Build Tools
Classifier: License :: OSI Approved :: MIT License
Classifier: Programming Language :: Python :: 3
Classifier: Programming Language :: Python :: 3.6
Classifier: Programming Language :: Python :: 3.7
Classifier: Programming Language :: Python :: 3.8
Requires-Dist: jsonrpcclient[aiohttp]
Requires-Dist: aiohttp (<4.0.0)
Provides-Extra: proxy
Requires-Dist: aiohttp-socks ; extra == 'proxy'
